enhancez/ZOO.py
enhancez/__init__.py
enhancez/constants.py
enhancez/display.py
enhancez/download.py
enhancez/file_utilities.py
enhancez/image_conversion.py
enhancez/image_processing.py
enhancez/input_validation.py
enhancez/resources.py
enhancez/run_streamlit.py
enhancez/.streamlit/config.toml
enhancez/pages/01_🫎_MOOSE.py
enhancez/pages/02_🦅_FALCON.py
enhancez/pages/03_🐾_PUMA.py
enhancez/pages/04_🦁_LION.py
enhancez-0.7.dist-info/METADATA
enhancez-0.7.dist-info/WHEEL
enhancez-0.7.dist-info/entry_points.txt
enhancez-0.7.dist-info/top_level.txt
enhancez-0.7.dist-info/RECORD
